searchf/__init__.py
searchf/app.py
searchf/colors.py
searchf/debug.py
searchf/enums.py
searchf/help.txt
searchf/keys.py
searchf/main.py
searchf/models.py
searchf/segments.py
searchf/sgr.py
searchf/storage.py
searchf/types.py
searchf/utils.py
searchf/views.py
searchf/test/__init__.py
searchf/test/all.py
searchf/test/color.py
searchf/test/rulers.txt
searchf/test/sample.txt
searchf/test/sample_bug.txt
searchf/test/sample_international.txt
searchf/test/sample_with_colors.txt
searchf/test/test_colors.py
searchf/test/test_enums.py
searchf/test/test_keys.py
searchf/test/test_models.py
searchf/test/test_segments.py
searchf/test/test_sgr.py
searchf/test/test_storage.py
searchf-1.26.dist-info/licenses/LICENSE
searchf-1.26.dist-info/METADATA
searchf-1.26.dist-info/WHEEL
searchf-1.26.dist-info/entry_points.txt
searchf-1.26.dist-info/top_level.txt
searchf-1.26.dist-info/RECORD
