Metadata-Version: 2.4
Name: searchf
Version: 1.26
Summary: A text-based application running in terminals to search into text files
Home-page: https://github.com/human3/searchf
Author: Adrien Felon
License-Expression: Apache-2.0
Project-URL: Homepage, https://github.com/human3/searchf
Keywords: search,file,terminal,console,highlighter,keyword,curses,utilities
Requires-Python: >=3.9
License-File: LICENSE
Dynamic: license-file
